mod4.py
mod4-1.0.1.dist-info/LICENSE
mod4-1.0.1.dist-info/METADATA
mod4-1.0.1.dist-info/WHEEL
mod4-1.0.1.dist-info/top_level.txt
mod4-1.0.1.dist-info/RECORD
