Metadata-Version: 2.1
Name: mod4
Version: 1.0.1
Summary: Test class for study
Home-page: https://github.com/czarny25/mod3.git
Author: ziejaCode
Author-email: czarny25101@gmail.com
License: MIT
Platform: UNKNOWN
